black_widow/__init__.py
black_widow/black_widow.py
black_widow/app/__init__.py
black_widow/app/env.py
black_widow/app/arguments/__init__.py
black_widow/app/arguments/input_arguments.py
black_widow/app/gui/__init__.py
black_widow/app/gui/manage.py
black_widow/app/gui/web/__init__.py
black_widow/app/gui/web/settings.py
black_widow/app/gui/web/urls.py
black_widow/app/gui/web/wsgi.py
black_widow/app/gui/web/black_widow/__init__.py
black_widow/app/gui/web/black_widow/admin.py
black_widow/app/gui/web/black_widow/apps.py
black_widow/app/gui/web/black_widow/tests.py
black_widow/app/gui/web/black_widow/urls.py
black_widow/app/gui/web/black_widow/models/__init__.py
black_widow/app/gui/web/black_widow/models/abstract_job_model.py
black_widow/app/gui/web/black_widow/models/abstract_model.py
black_widow/app/gui/web/black_widow/models/sniffing/__init__.py
black_widow/app/gui/web/black_widow/models/sniffing/sniffing_job_model.py
black_widow/app/gui/web/black_widow/models/web/__init__.py
black_widow/app/gui/web/black_widow/models/web/parsing/__init__.py
black_widow/app/gui/web/black_widow/models/web/parsing/web_parsing_job_model.py
black_widow/app/gui/web/black_widow/static/favicon.ico
black_widow/app/gui/web/black_widow/static/css/black-widow.css
black_widow/app/gui/web/black_widow/static/css/font-awesome.min.css
black_widow/app/gui/web/black_widow/static/css/google-fonts.css
black_widow/app/gui/web/black_widow/static/css/material-dashboard.min.css
black_widow/app/gui/web/black_widow/static/css/plugins/simplePagination.css
black_widow/app/gui/web/black_widow/static/fonts/fa/fontawesome-webfont.eot
black_widow/app/gui/web/black_widow/static/fonts/fa/fontawesome-webfont.svg
black_widow/app/gui/web/black_widow/static/fonts/fa/fontawesome-webfont.ttf
black_widow/app/gui/web/black_widow/static/fonts/fa/fontawesome-webfont.woff
black_widow/app/gui/web/black_widow/static/fonts/fa/fontawesome-webfont.woff2
black_widow/app/gui/web/black_widow/static/fonts/google/LICENSE.txt
black_widow-1.9.0.dist-info/LICENSE.txt
black_widow-1.9.0.dist-info/METADATA
black_widow-1.9.0.dist-info/WHEEL
black_widow-1.9.0.dist-info/entry_points.txt
black_widow-1.9.0.dist-info/top_level.txt
black_widow-1.9.0.dist-info/RECORD
