Metadata-Version: 2.1
Name: black-widow
Version: 1.9.0
Summary: Offensive penetration testing tool
Home-page: https://black-widow.it
Author: Fabrizio Fubelli
Author-email: fabrizio@fubelli.org
License: UNKNOWN
Project-URL: Documentation, https://github.com/offensive-hub/black-widow
Project-URL: Source, https://github.com/offensive-hub/black-widow
Project-URL: Tracker, https://github.com/offensive-hub/black-widow/issues
Keywords: black-widow penetration testing offensive cyber security pentest sniffing
Platform: UNKNOWN
Classifier: Programming Language :: Python :: 3
Classifier: License :: OSI Approved :: GNU General Public License v3 or later (GPLv3+)
Classifier: Operating System :: OS Independent
Classifier: Development Status :: 4 - Beta
Classifier: Environment :: Web Environment
Classifier: Natural Language :: English
Classifier: Topic :: Education :: Testing
Classifier: Topic :: Software Development :: Build Tools
Classifier: Topic :: System :: Clustering
Classifier: Topic :: System :: Monitoring
Classifier: Topic :: System :: Networking
Classifier: Topic :: System :: Hardware :: Symmetric Multi-processing
Classifier: Topic :: Utilities
Requires-Python: >=3.6
Requires-Dist: anytree
Requires-Dist: django
Requires-Dist: gunicorn
Requires-Dist: lxml
Requires-Dist: netifaces
Requires-Dist: numpy
Requires-Dist: pyshark
Requires-Dist: pytidylib
Requires-Dist: requests
Requires-Dist: simplejson
Requires-Dist: sqlmap
Requires-Dist: termcolor
Requires-Dist: urllib3
